sentoo/__init__.py
sentoo/_compat.py
sentoo/async_client.py
sentoo/client.py
sentoo/py.typed
sentoo-0.2.0.dist-info/METADATA
sentoo-0.2.0.dist-info/WHEEL
sentoo-0.2.0.dist-info/RECORD
