Metadata-Version: 2.4
Name: sentoo
Version: 0.2.0
Summary: A client library for Sentoo.io
Author-email: Lemi Boyce <lemuelboyce@gmail.com>
Requires-Python: >=3.12
Requires-Dist: httpx>=0.28.1
Requires-Dist: pydantic>=2.11.4
